catnekaise_cdk_iam_utilities/__init__.py
catnekaise_cdk_iam_utilities/py.typed
catnekaise_cdk_iam_utilities/_jsii/__init__.py
catnekaise_cdk_iam_utilities/_jsii/cdk-iam-utilities@0.0.33.jsii.tgz
catnekaise.cdk_iam_utilities-0.0.33.dist-info/LICENSE
catnekaise.cdk_iam_utilities-0.0.33.dist-info/METADATA
catnekaise.cdk_iam_utilities-0.0.33.dist-info/WHEEL
catnekaise.cdk_iam_utilities-0.0.33.dist-info/top_level.txt
catnekaise.cdk_iam_utilities-0.0.33.dist-info/RECORD
